{
    "_id": "SkullHM",
    "_name": "SkullHM",
    "_parent": "5a341c4686f77469e155819e",
    "_props": {
        "AnimationVariantsNumber": 0,
        "ArmorMaterial": "UHMWPE",
        "ArmorType": "None",
        "BackgroundColor": "violet",
        "BlindnessProtection": 0,
        "BlocksEarpiece": false,
        "BlocksEyewear": false,
        "BlocksFaceCover": false,
        "BlocksHeadwear": false,
        "BluntThroughput": 0,
        "CanPutIntoDuringTheRaid": true,
        "CanRequireOnRagfair": false,
        "CanSellOnRagfair": true,
        "CantRemoveFromSlotsDuringRaid": [],
        "ConflictingItems": [],
        "DeafStrength": "None",
        "Description": "SkullHM",
        "DiscardLimit": 1,
        "DiscardingBlock": false,
        "DropSoundType": "None",
        "Durability": 100,
        "ExamineExperience": 100,
        "ExamineTime": 1,
        "ExaminedByDefault": false,
        "ExtraSizeDown": 0,
        "ExtraSizeForceAdd": false,
        "ExtraSizeLeft": 0,
        "ExtraSizeRight": 0,
        "ExtraSizeUp": 0,
        "FaceShieldComponent": false,
        "FaceShieldMask": "NoMask",
        "Grids": [],
        "HasHinge": false,
        "Height": 1,
        "HideEntrails": false,
        "Indestructibility": 0.9,
        "InsuranceDisabled": false,
        "IsAlwaysAvailableForInsurance": true,
        "IsLockedafterEquip": false,
        "IsSpecialSlotOnly": false,
        "IsUnbuyable": false,
        "IsUndiscardable": false,
        "IsUngivable": false,
        "IsUnremovable": false,
        "IsUnsaleable": false,
        "ItemSound": "gear_generic",
        "LootExperience": 5,
        "MaterialType": "BodyArmor",
        "MaxDurability": 100,
        "MergesWithChildren": false,
        "Name": "SkullHM",
        "NotShownInSlot": false,
        "Prefab": {
            "path": "FaceCover/item_equipment_facecover_skull_half_mask.bundle",
            "rcid": ""
        },
        "QuestItem": false,
        "QuestStashMaxCount": 0,
        "RagFairCommissionModifier": 1,
        "RepairCost": 0,
        "RepairSpeed": 0,
        "RicochetParams": {
            "x": 0,
            "y": 0,
            "z": 80
        },
        "ShortName": "SkullHM",
        "Slots": [],
        "StackMaxSize": 1,
        "StackObjectsCount": 1,
        "Unlootable": false,
        "UnlootableFromSide": [],
        "UnlootableFromSlot": "FirstPrimaryWeapon",
        "UsePrefab": {
            "path": "",
            "rcid": ""
        },
        "Weight": 0.1,
        "Width": 1,
        "armorClass": "0",
        "armorZone": [],
        "headSegments": [],
        "mousePenalty": 0,
        "speedPenaltyPercent": 0,
        "weaponErgonomicPenalty": 0
    },
    "_proto": "572b7d8524597762b472f9d1",
    "_type": "Item"
}